CHANGES.rst
CONTRIBUTORS.rst
LICENSE.GPL
LICENSE.rst
MANIFEST.in
README.rst
setup.cfg
setup.py
docs/index.rst
src/ideabox/__init__.py
src/ideabox.stats.egg-info/PKG-INFO
src/ideabox.stats.egg-info/SOURCES.txt
src/ideabox.stats.egg-info/dependency_links.txt
src/ideabox.stats.egg-info/entry_points.txt
src/ideabox.stats.egg-info/namespace_packages.txt
src/ideabox.stats.egg-info/not-zip-safe
src/ideabox.stats.egg-info/requires.txt
src/ideabox.stats.egg-info/top_level.txt
src/ideabox/stats/__init__.py
src/ideabox/stats/configure.zcml
src/ideabox/stats/interfaces.py
src/ideabox/stats/setuphandlers.py
src/ideabox/stats/testing.py
src/ideabox/stats/upgrades.py
src/ideabox/stats/upgrades.zcml
src/ideabox/stats/utils.py
src/ideabox/stats/browser/__init__.py
src/ideabox/stats/browser/configure.zcml
src/ideabox/stats/browser/overrides/.gitkeep
src/ideabox/stats/browser/static/.gitkeep
src/ideabox/stats/locales/update.sh
src/ideabox/stats/profiles/default/actions.xml
src/ideabox/stats/profiles/default/browserlayer.xml
src/ideabox/stats/profiles/default/catalog.xml
src/ideabox/stats/profiles/default/metadata.xml
src/ideabox/stats/profiles/default/registry.xml
src/ideabox/stats/profiles/uninstall/browserlayer.xml
src/ideabox/stats/tests/__init__.py
src/ideabox/stats/tests/test_setup.py